{
  "fon_kodu": "HVI",
  "fon_unvan": "DENİZ PORTFÖY HOLDİNGLER VE İŞTİRAKLERİ HİSSE SENEDİ (TL) FONU (HİSSE SENEDİ YOĞUN FON)",
  "fontip": "YAT",
  "baslangic": "2021-04-30",
  "bitis": "2026-04-29",
  "kaynak": "https://fundturkey.com.tr",
  "kayit_sayisi": 145,
  "gun_kapsami": 208,
  "durum_panel": "veri_eksik",
  "neden": "bes_yildan_kisa",
  "veri": [
    {
      "TARIH": "1759449600000",
      "FONKODU": "HVI",
      "FONUNVAN": "DENİZ PORTFÖY HOLDİNGLER VE İŞTİRAKLERİ HİSSE SENEDİ (TL) FONU (HİSSE SENEDİ YOĞUN FON)",
      "FIYAT": 0.0,
      "TEDPAYSAYISI": null,
      "KISISAYISI": null,
      "PORTFOYBUYUKLUK": null,
      "BilFiyat": "-"
    },
    {
      "TARIH": "1759708800000",
      "FONKODU": "HVI",
      "FONUNVAN": "DENİZ PORTFÖY HOLDİNGLER VE İŞTİRAKLERİ HİSSE SENEDİ (TL) FONU (HİSSE SENEDİ YOĞUN FON)",
      "FIYAT": 0.0,
      "TEDPAYSAYISI": null,
      "KISISAYISI": null,
      "PORTFOYBUYUKLUK": null,
      "BilFiyat": "-"
    },
    {
      "TARIH": "1759795200000",
      "FONKODU": "HVI",
      "FONUNVAN": "DENİZ PORTFÖY HOLDİNGLER VE İŞTİRAKLERİ HİSSE SENEDİ (TL) FONU (HİSSE SENEDİ YOĞUN FON)",
      "FIYAT": 0.0,
      "TEDPAYSAYISI": null,
      "KISISAYISI": null,
      "PORTFOYBUYUKLUK": null,
      "BilFiyat": "-"
    },
    {
      "TARIH": "1759881600000",
      "FONKODU": "HVI",
      "FONUNVAN": "DENİZ PORTFÖY HOLDİNGLER VE İŞTİRAKLERİ HİSSE SENEDİ (TL) FONU (HİSSE SENEDİ YOĞUN FON)",
      "FIYAT": 0.0,
      "TEDPAYSAYISI": null,
      "KISISAYISI": null,
      "PORTFOYBUYUKLUK": null,
      "BilFiyat": "-"
    },
    {
      "TARIH": "1759968000000",
      "FONKODU": "HVI",
      "FONUNVAN": "DENİZ PORTFÖY HOLDİNGLER VE İŞTİRAKLERİ HİSSE SENEDİ (TL) FONU (HİSSE SENEDİ YOĞUN FON)",
      "FIYAT": 0.0,
      "TEDPAYSAYISI": null,
      "KISISAYISI": null,
      "PORTFOYBUYUKLUK": null,
      "BilFiyat": "-"
    },
    {
      "TARIH": "1760054400000",
      "FONKODU": "HVI",
      "FONUNVAN": "DENİZ PORTFÖY HOLDİNGLER VE İŞTİRAKLERİ HİSSE SENEDİ (TL) FONU (HİSSE SENEDİ YOĞUN FON)",
      "FIYAT": 0.0,
      "TEDPAYSAYISI": null,
      "KISISAYISI": null,
      "PORTFOYBUYUKLUK": null,
      "BilFiyat": "-"
    },
    {
      "TARIH": "1760313600000",
      "FONKODU": "HVI",
      "FONUNVAN": "DENİZ PORTFÖY HOLDİNGLER VE İŞTİRAKLERİ HİSSE SENEDİ (TL) FONU (HİSSE SENEDİ YOĞUN FON)",
      "FIYAT": 0.0,
      "TEDPAYSAYISI": null,
      "KISISAYISI": null,
      "PORTFOYBUYUKLUK": null,
      "BilFiyat": "-"
    },
    {
      "TARIH": "1760400000000",
      "FONKODU": "HVI",
      "FONUNVAN": "DENİZ PORTFÖY HOLDİNGLER VE İŞTİRAKLERİ HİSSE SENEDİ (TL) FONU (HİSSE SENEDİ YOĞUN FON)",
      "FIYAT": 0.0,
      "TEDPAYSAYISI": null,
      "KISISAYISI": null,
      "PORTFOYBUYUKLUK": null,
      "BilFiyat": "-"
    },
    {
      "TARIH": "1760486400000",
      "FONKODU": "HVI",
      "FONUNVAN": "DENİZ PORTFÖY HOLDİNGLER VE İŞTİRAKLERİ HİSSE SENEDİ (TL) FONU (HİSSE SENEDİ YOĞUN FON)",
      "FIYAT": 0.0,
      "TEDPAYSAYISI": null,
      "KISISAYISI": null,
      "PORTFOYBUYUKLUK": null,
      "BilFiyat": "-"
    },
    {
      "TARIH": "1760572800000",
      "FONKODU": "HVI",
      "FONUNVAN": "DENİZ PORTFÖY HOLDİNGLER VE İŞTİRAKLERİ HİSSE SENEDİ (TL) FONU (HİSSE SENEDİ YOĞUN FON)",
      "FIYAT": 0.0,
      "TEDPAYSAYISI": null,
      "KISISAYISI": null,
      "PORTFOYBUYUKLUK": null,
      "BilFiyat": "-"
    },
    {
      "TARIH": "1760659200000",
      "FONKODU": "HVI",
      "FONUNVAN": "DENİZ PORTFÖY HOLDİNGLER VE İŞTİRAKLERİ HİSSE SENEDİ (TL) FONU (HİSSE SENEDİ YOĞUN FON)",
      "FIYAT": 0.0,
      "TEDPAYSAYISI": null,
      "KISISAYISI": null,
      "PORTFOYBUYUKLUK": null,
      "BilFiyat": "-"
    },
    {
      "TARIH": "1760918400000",
      "FONKODU": "HVI",
      "FONUNVAN": "DENİZ PORTFÖY HOLDİNGLER VE İŞTİRAKLERİ HİSSE SENEDİ (TL) FONU (HİSSE SENEDİ YOĞUN FON)",
      "FIYAT": 0.0,
      "TEDPAYSAYISI": null,
      "KISISAYISI": null,
      "PORTFOYBUYUKLUK": null,
      "BilFiyat": "-"
    },
    {
      "TARIH": "1761004800000",
      "FONKODU": "HVI",
      "FONUNVAN": "DENİZ PORTFÖY HOLDİNGLER VE İŞTİRAKLERİ HİSSE SENEDİ (TL) FONU (HİSSE SENEDİ YOĞUN FON)",
      "FIYAT": 0.0,
      "TEDPAYSAYISI": null,
      "KISISAYISI": null,
      "PORTFOYBUYUKLUK": null,
      "BilFiyat": "-"
    },
    {
      "TARIH": "1761091200000",
      "FONKODU": "HVI",
      "FONUNVAN": "DENİZ PORTFÖY HOLDİNGLER VE İŞTİRAKLERİ HİSSE SENEDİ (TL) FONU (HİSSE SENEDİ YOĞUN FON)",
      "FIYAT": 0.0,
      "TEDPAYSAYISI": null,
      "KISISAYISI": null,
      "PORTFOYBUYUKLUK": null,
      "BilFiyat": "-"
    },
    {
      "TARIH": "1761177600000",
      "FONKODU": "HVI",
      "FONUNVAN": "DENİZ PORTFÖY HOLDİNGLER VE İŞTİRAKLERİ HİSSE SENEDİ (TL) FONU (HİSSE SENEDİ YOĞUN FON)",
      "FIYAT": 0.0,
      "TEDPAYSAYISI": null,
      "KISISAYISI": null,
      "PORTFOYBUYUKLUK": null,
      "BilFiyat": "-"
    },
    {
      "TARIH": "1761264000000",
      "FONKODU": "HVI",
      "FONUNVAN": "DENİZ PORTFÖY HOLDİNGLER VE İŞTİRAKLERİ HİSSE SENEDİ (TL) FONU (HİSSE SENEDİ YOĞUN FON)",
      "FIYAT": 0.0,
      "TEDPAYSAYISI": null,
      "KISISAYISI": null,
      "PORTFOYBUYUKLUK": null,
      "BilFiyat": "-"
    },
    {
      "TARIH": "1761523200000",
      "FONKODU": "HVI",
      "FONUNVAN": "DENİZ PORTFÖY HOLDİNGLER VE İŞTİRAKLERİ HİSSE SENEDİ (TL) FONU (HİSSE SENEDİ YOĞUN FON)",
      "FIYAT": 0.0,
      "TEDPAYSAYISI": null,
      "KISISAYISI": null,
      "PORTFOYBUYUKLUK": null,
      "BilFiyat": "-"
    },
    {
      "TARIH": "1761609600000",
      "FONKODU": "HVI",
      "FONUNVAN": "DENİZ PORTFÖY HOLDİNGLER VE İŞTİRAKLERİ HİSSE SENEDİ (TL) FONU (HİSSE SENEDİ YOĞUN FON)",
      "FIYAT": 0.0,
      "TEDPAYSAYISI": null,
      "KISISAYISI": null,
      "PORTFOYBUYUKLUK": null,
      "BilFiyat": "-"
    },
    {
      "TARIH": "1761782400000",
      "FONKODU": "HVI",
      "FONUNVAN": "DENİZ PORTFÖY HOLDİNGLER VE İŞTİRAKLERİ HİSSE SENEDİ (TL) FONU (HİSSE SENEDİ YOĞUN FON)",
      "FIYAT": 1.000765,
      "TEDPAYSAYISI": null,
      "KISISAYISI": null,
      "PORTFOYBUYUKLUK": null,
      "BilFiyat": "-"
    },
    {
      "TARIH": "1761868800000",
      "FONKODU": "HVI",
      "FONUNVAN": "DENİZ PORTFÖY HOLDİNGLER VE İŞTİRAKLERİ HİSSE SENEDİ (TL) FONU (HİSSE SENEDİ YOĞUN FON)",
      "FIYAT": 1.00583,
      "TEDPAYSAYISI": null,
      "KISISAYISI": null,
      "PORTFOYBUYUKLUK": null,
      "BilFiyat": "-"
    },
    {
      "TARIH": "1762128000000",
      "FONKODU": "HVI",
      "FONUNVAN": "DENİZ PORTFÖY HOLDİNGLER VE İŞTİRAKLERİ HİSSE SENEDİ (TL) FONU (HİSSE SENEDİ YOĞUN FON)",
      "FIYAT": 1.017135,
      "TEDPAYSAYISI": null,
      "KISISAYISI": null,
      "PORTFOYBUYUKLUK": null,
      "BilFiyat": "-"
    },
    {
      "TARIH": "1762214400000",
      "FONKODU": "HVI",
      "FONUNVAN": "DENİZ PORTFÖY HOLDİNGLER VE İŞTİRAKLERİ HİSSE SENEDİ (TL) FONU (HİSSE SENEDİ YOĞUN FON)",
      "FIYAT": 1.026276,
      "TEDPAYSAYISI": null,
      "KISISAYISI": null,
      "PORTFOYBUYUKLUK": null,
      "BilFiyat": "-"
    },
    {
      "TARIH": "1762300800000",
      "FONKODU": "HVI",
      "FONUNVAN": "DENİZ PORTFÖY HOLDİNGLER VE İŞTİRAKLERİ HİSSE SENEDİ (TL) FONU (HİSSE SENEDİ YOĞUN FON)",
      "FIYAT": 1.015887,
      "TEDPAYSAYISI": null,
      "KISISAYISI": null,
      "PORTFOYBUYUKLUK": null,
      "BilFiyat": "-"
    },
    {
      "TARIH": "1762387200000",
      "FONKODU": "HVI",
      "FONUNVAN": "DENİZ PORTFÖY HOLDİNGLER VE İŞTİRAKLERİ HİSSE SENEDİ (TL) FONU (HİSSE SENEDİ YOĞUN FON)",
      "FIYAT": 1.020401,
      "TEDPAYSAYISI": null,
      "KISISAYISI": null,
      "PORTFOYBUYUKLUK": null,
      "BilFiyat": "-"
    },
    {
      "TARIH": "1762473600000",
      "FONKODU": "HVI",
      "FONUNVAN": "DENİZ PORTFÖY HOLDİNGLER VE İŞTİRAKLERİ HİSSE SENEDİ (TL) FONU (HİSSE SENEDİ YOĞUN FON)",
      "FIYAT": 1.033377,
      "TEDPAYSAYISI": null,
      "KISISAYISI": null,
      "PORTFOYBUYUKLUK": null,
      "BilFiyat": "-"
    },
    {
      "TARIH": "1762732800000",
      "FONKODU": "HVI",
      "FONUNVAN": "DENİZ PORTFÖY HOLDİNGLER VE İŞTİRAKLERİ HİSSE SENEDİ (TL) FONU (HİSSE SENEDİ YOĞUN FON)",
      "FIYAT": 1.022032,
      "TEDPAYSAYISI": null,
      "KISISAYISI": null,
      "PORTFOYBUYUKLUK": null,
      "BilFiyat": "-"
    },
    {
      "TARIH": "1762819200000",
      "FONKODU": "HVI",
      "FONUNVAN": "DENİZ PORTFÖY HOLDİNGLER VE İŞTİRAKLERİ HİSSE SENEDİ (TL) FONU (HİSSE SENEDİ YOĞUN FON)",
      "FIYAT": 1.011633,
      "TEDPAYSAYISI": null,
      "KISISAYISI": null,
      "PORTFOYBUYUKLUK": null,
      "BilFiyat": "-"
    },
    {
      "TARIH": "1762905600000",
      "FONKODU": "HVI",
      "FONUNVAN": "DENİZ PORTFÖY HOLDİNGLER VE İŞTİRAKLERİ HİSSE SENEDİ (TL) FONU (HİSSE SENEDİ YOĞUN FON)",
      "FIYAT": 0.993802,
      "TEDPAYSAYISI": null,
      "KISISAYISI": null,
      "PORTFOYBUYUKLUK": null,
      "BilFiyat": "-"
    },
    {
      "TARIH": "1762992000000",
      "FONKODU": "HVI",
      "FONUNVAN": "DENİZ PORTFÖY HOLDİNGLER VE İŞTİRAKLERİ HİSSE SENEDİ (TL) FONU (HİSSE SENEDİ YOĞUN FON)",
      "FIYAT": 0.996632,
      "TEDPAYSAYISI": null,
      "KISISAYISI": null,
      "PORTFOYBUYUKLUK": null,
      "BilFiyat": "-"
    },
    {
      "TARIH": "1763078400000",
      "FONKODU": "HVI",
      "FONUNVAN": "DENİZ PORTFÖY HOLDİNGLER VE İŞTİRAKLERİ HİSSE SENEDİ (TL) FONU (HİSSE SENEDİ YOĞUN FON)",
      "FIYAT": 0.997266,
      "TEDPAYSAYISI": null,
      "KISISAYISI": null,
      "PORTFOYBUYUKLUK": null,
      "BilFiyat": "-"
    },
    {
      "TARIH": "1763337600000",
      "FONKODU": "HVI",
      "FONUNVAN": "DENİZ PORTFÖY HOLDİNGLER VE İŞTİRAKLERİ HİSSE SENEDİ (TL) FONU (HİSSE SENEDİ YOĞUN FON)",
      "FIYAT": 0.990126,
      "TEDPAYSAYISI": null,
      "KISISAYISI": null,
      "PORTFOYBUYUKLUK": null,
      "BilFiyat": "-"
    },
    {
      "TARIH": "1763424000000",
      "FONKODU": "HVI",
      "FONUNVAN": "DENİZ PORTFÖY HOLDİNGLER VE İŞTİRAKLERİ HİSSE SENEDİ (TL) FONU (HİSSE SENEDİ YOĞUN FON)",
      "FIYAT": 0.99947,
      "TEDPAYSAYISI": null,
      "KISISAYISI": null,
      "PORTFOYBUYUKLUK": null,
      "BilFiyat": "-"
    },
    {
      "TARIH": "1763510400000",
      "FONKODU": "HVI",
      "FONUNVAN": "DENİZ PORTFÖY HOLDİNGLER VE İŞTİRAKLERİ HİSSE SENEDİ (TL) FONU (HİSSE SENEDİ YOĞUN FON)",
      "FIYAT": 1.001222,
      "TEDPAYSAYISI": null,
      "KISISAYISI": null,
      "PORTFOYBUYUKLUK": null,
      "BilFiyat": "-"
    },
    {
      "TARIH": "1763596800000",
      "FONKODU": "HVI",
      "FONUNVAN": "DENİZ PORTFÖY HOLDİNGLER VE İŞTİRAKLERİ HİSSE SENEDİ (TL) FONU (HİSSE SENEDİ YOĞUN FON)",
      "FIYAT": 1.017545,
      "TEDPAYSAYISI": null,
      "KISISAYISI": null,
      "PORTFOYBUYUKLUK": null,
      "BilFiyat": "-"
    },
    {
      "TARIH": "1763683200000",
      "FONKODU": "HVI",
      "FONUNVAN": "DENİZ PORTFÖY HOLDİNGLER VE İŞTİRAKLERİ HİSSE SENEDİ (TL) FONU (HİSSE SENEDİ YOĞUN FON)",
      "FIYAT": 1.022679,
      "TEDPAYSAYISI": null,
      "KISISAYISI": null,
      "PORTFOYBUYUKLUK": null,
      "BilFiyat": "-"
    },
    {
      "TARIH": "1763942400000",
      "FONKODU": "HVI",
      "FONUNVAN": "DENİZ PORTFÖY HOLDİNGLER VE İŞTİRAKLERİ HİSSE SENEDİ (TL) FONU (HİSSE SENEDİ YOĞUN FON)",
      "FIYAT": 1.015542,
      "TEDPAYSAYISI": null,
      "KISISAYISI": null,
      "PORTFOYBUYUKLUK": null,
      "BilFiyat": "-"
    },
    {
      "TARIH": "1764028800000",
      "FONKODU": "HVI",
      "FONUNVAN": "DENİZ PORTFÖY HOLDİNGLER VE İŞTİRAKLERİ HİSSE SENEDİ (TL) FONU (HİSSE SENEDİ YOĞUN FON)",
      "FIYAT": 1.015469,
      "TEDPAYSAYISI": null,
      "KISISAYISI": null,
      "PORTFOYBUYUKLUK": null,
      "BilFiyat": "-"
    },
    {
      "TARIH": "1764115200000",
      "FONKODU": "HVI",
      "FONUNVAN": "DENİZ PORTFÖY HOLDİNGLER VE İŞTİRAKLERİ HİSSE SENEDİ (TL) FONU (HİSSE SENEDİ YOĞUN FON)",
      "FIYAT": 1.015576,
      "TEDPAYSAYISI": null,
      "KISISAYISI": null,
      "PORTFOYBUYUKLUK": null,
      "BilFiyat": "-"
    },
    {
      "TARIH": "1764201600000",
      "FONKODU": "HVI",
      "FONUNVAN": "DENİZ PORTFÖY HOLDİNGLER VE İŞTİRAKLERİ HİSSE SENEDİ (TL) FONU (HİSSE SENEDİ YOĞUN FON)",
      "FIYAT": 1.018717,
      "TEDPAYSAYISI": null,
      "KISISAYISI": null,
      "PORTFOYBUYUKLUK": null,
      "BilFiyat": "-"
    },
    {
      "TARIH": "1764288000000",
      "FONKODU": "HVI",
      "FONUNVAN": "DENİZ PORTFÖY HOLDİNGLER VE İŞTİRAKLERİ HİSSE SENEDİ (TL) FONU (HİSSE SENEDİ YOĞUN FON)",
      "FIYAT": 1.026501,
      "TEDPAYSAYISI": null,
      "KISISAYISI": null,
      "PORTFOYBUYUKLUK": null,
      "BilFiyat": "-"
    },
    {
      "TARIH": "1764547200000",
      "FONKODU": "HVI",
      "FONUNVAN": "DENİZ PORTFÖY HOLDİNGLER VE İŞTİRAKLERİ HİSSE SENEDİ (TL) FONU (HİSSE SENEDİ YOĞUN FON)",
      "FIYAT": 1.01992,
      "TEDPAYSAYISI": null,
      "KISISAYISI": null,
      "PORTFOYBUYUKLUK": null,
      "BilFiyat": "-"
    },
    {
      "TARIH": "1764633600000",
      "FONKODU": "HVI",
      "FONUNVAN": "DENİZ PORTFÖY HOLDİNGLER VE İŞTİRAKLERİ HİSSE SENEDİ (TL) FONU (HİSSE SENEDİ YOĞUN FON)",
      "FIYAT": 1.04258,
      "TEDPAYSAYISI": null,
      "KISISAYISI": null,
      "PORTFOYBUYUKLUK": null,
      "BilFiyat": "-"
    },
    {
      "TARIH": "1764720000000",
      "FONKODU": "HVI",
      "FONUNVAN": "DENİZ PORTFÖY HOLDİNGLER VE İŞTİRAKLERİ HİSSE SENEDİ (TL) FONU (HİSSE SENEDİ YOĞUN FON)",
      "FIYAT": 1.041722,
      "TEDPAYSAYISI": null,
      "KISISAYISI": null,
      "PORTFOYBUYUKLUK": null,
      "BilFiyat": "-"
    },
    {
      "TARIH": "1764806400000",
      "FONKODU": "HVI",
      "FONUNVAN": "DENİZ PORTFÖY HOLDİNGLER VE İŞTİRAKLERİ HİSSE SENEDİ (TL) FONU (HİSSE SENEDİ YOĞUN FON)",
      "FIYAT": 1.041867,
      "TEDPAYSAYISI": null,
      "KISISAYISI": null,
      "PORTFOYBUYUKLUK": null,
      "BilFiyat": "-"
    },
    {
      "TARIH": "1764892800000",
      "FONKODU": "HVI",
      "FONUNVAN": "DENİZ PORTFÖY HOLDİNGLER VE İŞTİRAKLERİ HİSSE SENEDİ (TL) FONU (HİSSE SENEDİ YOĞUN FON)",
      "FIYAT": 1.030753,
      "TEDPAYSAYISI": null,
      "KISISAYISI": null,
      "PORTFOYBUYUKLUK": null,
      "BilFiyat": "-"
    },
    {
      "TARIH": "1765152000000",
      "FONKODU": "HVI",
      "FONUNVAN": "DENİZ PORTFÖY HOLDİNGLER VE İŞTİRAKLERİ HİSSE SENEDİ (TL) FONU (HİSSE SENEDİ YOĞUN FON)",
      "FIYAT": 1.040944,
      "TEDPAYSAYISI": null,
      "KISISAYISI": null,
      "PORTFOYBUYUKLUK": null,
      "BilFiyat": "-"
    },
    {
      "TARIH": "1765238400000",
      "FONKODU": "HVI",
      "FONUNVAN": "DENİZ PORTFÖY HOLDİNGLER VE İŞTİRAKLERİ HİSSE SENEDİ (TL) FONU (HİSSE SENEDİ YOĞUN FON)",
      "FIYAT": 1.059101,
      "TEDPAYSAYISI": null,
      "KISISAYISI": null,
      "PORTFOYBUYUKLUK": null,
      "BilFiyat": "-"
    },
    {
      "TARIH": "1765324800000",
      "FONKODU": "HVI",
      "FONUNVAN": "DENİZ PORTFÖY HOLDİNGLER VE İŞTİRAKLERİ HİSSE SENEDİ (TL) FONU (HİSSE SENEDİ YOĞUN FON)",
      "FIYAT": 1.060516,
      "TEDPAYSAYISI": null,
      "KISISAYISI": null,
      "PORTFOYBUYUKLUK": null,
      "BilFiyat": "-"
    },
    {
      "TARIH": "1765411200000",
      "FONKODU": "HVI",
      "FONUNVAN": "DENİZ PORTFÖY HOLDİNGLER VE İŞTİRAKLERİ HİSSE SENEDİ (TL) FONU (HİSSE SENEDİ YOĞUN FON)",
      "FIYAT": 1.057131,
      "TEDPAYSAYISI": null,
      "KISISAYISI": null,
      "PORTFOYBUYUKLUK": null,
      "BilFiyat": "-"
    },
    {
      "TARIH": "1765497600000",
      "FONKODU": "HVI",
      "FONUNVAN": "DENİZ PORTFÖY HOLDİNGLER VE İŞTİRAKLERİ HİSSE SENEDİ (TL) FONU (HİSSE SENEDİ YOĞUN FON)",
      "FIYAT": 1.060543,
      "TEDPAYSAYISI": null,
      "KISISAYISI": null,
      "PORTFOYBUYUKLUK": null,
      "BilFiyat": "-"
    },
    {
      "TARIH": "1765756800000",
      "FONKODU": "HVI",
      "FONUNVAN": "DENİZ PORTFÖY HOLDİNGLER VE İŞTİRAKLERİ HİSSE SENEDİ (TL) FONU (HİSSE SENEDİ YOĞUN FON)",
      "FIYAT": 1.075234,
      "TEDPAYSAYISI": null,
      "KISISAYISI": null,
      "PORTFOYBUYUKLUK": null,
      "BilFiyat": "-"
    },
    {
      "TARIH": "1765843200000",
      "FONKODU": "HVI",
      "FONUNVAN": "DENİZ PORTFÖY HOLDİNGLER VE İŞTİRAKLERİ HİSSE SENEDİ (TL) FONU (HİSSE SENEDİ YOĞUN FON)",
      "FIYAT": 1.088134,
      "TEDPAYSAYISI": null,
      "KISISAYISI": null,
      "PORTFOYBUYUKLUK": null,
      "BilFiyat": "-"
    },
    {
      "TARIH": "1765929600000",
      "FONKODU": "HVI",
      "FONUNVAN": "DENİZ PORTFÖY HOLDİNGLER VE İŞTİRAKLERİ HİSSE SENEDİ (TL) FONU (HİSSE SENEDİ YOĞUN FON)",
      "FIYAT": 1.079561,
      "TEDPAYSAYISI": null,
      "KISISAYISI": null,
      "PORTFOYBUYUKLUK": null,
      "BilFiyat": "-"
    },
    {
      "TARIH": "1766016000000",
      "FONKODU": "HVI",
      "FONUNVAN": "DENİZ PORTFÖY HOLDİNGLER VE İŞTİRAKLERİ HİSSE SENEDİ (TL) FONU (HİSSE SENEDİ YOĞUN FON)",
      "FIYAT": 1.077803,
      "TEDPAYSAYISI": null,
      "KISISAYISI": null,
      "PORTFOYBUYUKLUK": null,
      "BilFiyat": "-"
    },
    {
      "TARIH": "1766102400000",
      "FONKODU": "HVI",
      "FONUNVAN": "DENİZ PORTFÖY HOLDİNGLER VE İŞTİRAKLERİ HİSSE SENEDİ (TL) FONU (HİSSE SENEDİ YOĞUN FON)",
      "FIYAT": 1.080434,
      "TEDPAYSAYISI": null,
      "KISISAYISI": null,
      "PORTFOYBUYUKLUK": null,
      "BilFiyat": "-"
    },
    {
      "TARIH": "1766361600000",
      "FONKODU": "HVI",
      "FONUNVAN": "DENİZ PORTFÖY HOLDİNGLER VE İŞTİRAKLERİ HİSSE SENEDİ (TL) FONU (HİSSE SENEDİ YOĞUN FON)",
      "FIYAT": 1.073614,
      "TEDPAYSAYISI": null,
      "KISISAYISI": null,
      "PORTFOYBUYUKLUK": null,
      "BilFiyat": "-"
    },
    {
      "TARIH": "1766448000000",
      "FONKODU": "HVI",
      "FONUNVAN": "DENİZ PORTFÖY HOLDİNGLER VE İŞTİRAKLERİ HİSSE SENEDİ (TL) FONU (HİSSE SENEDİ YOĞUN FON)",
      "FIYAT": 1.06893,
      "TEDPAYSAYISI": null,
      "KISISAYISI": null,
      "PORTFOYBUYUKLUK": null,
      "BilFiyat": "-"
    },
    {
      "TARIH": "1766534400000",
      "FONKODU": "HVI",
      "FONUNVAN": "DENİZ PORTFÖY HOLDİNGLER VE İŞTİRAKLERİ HİSSE SENEDİ (TL) FONU (HİSSE SENEDİ YOĞUN FON)",
      "FIYAT": 1.061475,
      "TEDPAYSAYISI": null,
      "KISISAYISI": null,
      "PORTFOYBUYUKLUK": null,
      "BilFiyat": "-"
    },
    {
      "TARIH": "1766620800000",
      "FONKODU": "HVI",
      "FONUNVAN": "DENİZ PORTFÖY HOLDİNGLER VE İŞTİRAKLERİ HİSSE SENEDİ (TL) FONU (HİSSE SENEDİ YOĞUN FON)",
      "FIYAT": 1.07039,
      "TEDPAYSAYISI": null,
      "KISISAYISI": null,
      "PORTFOYBUYUKLUK": null,
      "BilFiyat": "-"
    },
    {
      "TARIH": "1766707200000",
      "FONKODU": "HVI",
      "FONUNVAN": "DENİZ PORTFÖY HOLDİNGLER VE İŞTİRAKLERİ HİSSE SENEDİ (TL) FONU (HİSSE SENEDİ YOĞUN FON)",
      "FIYAT": 1.069623,
      "TEDPAYSAYISI": null,
      "KISISAYISI": null,
      "PORTFOYBUYUKLUK": null,
      "BilFiyat": "-"
    },
    {
      "TARIH": "1766966400000",
      "FONKODU": "HVI",
      "FONUNVAN": "DENİZ PORTFÖY HOLDİNGLER VE İŞTİRAKLERİ HİSSE SENEDİ (TL) FONU (HİSSE SENEDİ YOĞUN FON)",
      "FIYAT": 1.061343,
      "TEDPAYSAYISI": null,
      "KISISAYISI": null,
      "PORTFOYBUYUKLUK": null,
      "BilFiyat": "-"
    },
    {
      "TARIH": "1767052800000",
      "FONKODU": "HVI",
      "FONUNVAN": "DENİZ PORTFÖY HOLDİNGLER VE İŞTİRAKLERİ HİSSE SENEDİ (TL) FONU (HİSSE SENEDİ YOĞUN FON)",
      "FIYAT": 1.053977,
      "TEDPAYSAYISI": null,
      "KISISAYISI": null,
      "PORTFOYBUYUKLUK": null,
      "BilFiyat": "-"
    },
    {
      "TARIH": "1767139200000",
      "FONKODU": "HVI",
      "FONUNVAN": "DENİZ PORTFÖY HOLDİNGLER VE İŞTİRAKLERİ HİSSE SENEDİ (TL) FONU (HİSSE SENEDİ YOĞUN FON)",
      "FIYAT": 1.059623,
      "TEDPAYSAYISI": null,
      "KISISAYISI": null,
      "PORTFOYBUYUKLUK": null,
      "BilFiyat": "-"
    },
    {
      "TARIH": "1767312000000",
      "FONKODU": "HVI",
      "FONUNVAN": "DENİZ PORTFÖY HOLDİNGLER VE İŞTİRAKLERİ HİSSE SENEDİ (TL) FONU (HİSSE SENEDİ YOĞUN FON)",
      "FIYAT": 1.062199,
      "TEDPAYSAYISI": null,
      "KISISAYISI": null,
      "PORTFOYBUYUKLUK": null,
      "BilFiyat": "-"
    },
    {
      "TARIH": "1767571200000",
      "FONKODU": "HVI",
      "FONUNVAN": "DENİZ PORTFÖY HOLDİNGLER VE İŞTİRAKLERİ HİSSE SENEDİ (TL) FONU (HİSSE SENEDİ YOĞUN FON)",
      "FIYAT": 1.087052,
      "TEDPAYSAYISI": null,
      "KISISAYISI": null,
      "PORTFOYBUYUKLUK": null,
      "BilFiyat": "-"
    },
    {
      "TARIH": "1767657600000",
      "FONKODU": "HVI",
      "FONUNVAN": "DENİZ PORTFÖY HOLDİNGLER VE İŞTİRAKLERİ HİSSE SENEDİ (TL) FONU (HİSSE SENEDİ YOĞUN FON)",
      "FIYAT": 1.101538,
      "TEDPAYSAYISI": null,
      "KISISAYISI": null,
      "PORTFOYBUYUKLUK": null,
      "BilFiyat": "-"
    },
    {
      "TARIH": "1767744000000",
      "FONKODU": "HVI",
      "FONUNVAN": "DENİZ PORTFÖY HOLDİNGLER VE İŞTİRAKLERİ HİSSE SENEDİ (TL) FONU (HİSSE SENEDİ YOĞUN FON)",
      "FIYAT": 1.115537,
      "TEDPAYSAYISI": null,
      "KISISAYISI": null,
      "PORTFOYBUYUKLUK": null,
      "BilFiyat": "-"
    },
    {
      "TARIH": "1767830400000",
      "FONKODU": "HVI",
      "FONUNVAN": "DENİZ PORTFÖY HOLDİNGLER VE İŞTİRAKLERİ HİSSE SENEDİ (TL) FONU (HİSSE SENEDİ YOĞUN FON)",
      "FIYAT": 1.107515,
      "TEDPAYSAYISI": null,
      "KISISAYISI": null,
      "PORTFOYBUYUKLUK": null,
      "BilFiyat": "-"
    },
    {
      "TARIH": "1767916800000",
      "FONKODU": "HVI",
      "FONUNVAN": "DENİZ PORTFÖY HOLDİNGLER VE İŞTİRAKLERİ HİSSE SENEDİ (TL) FONU (HİSSE SENEDİ YOĞUN FON)",
      "FIYAT": 1.114185,
      "TEDPAYSAYISI": null,
      "KISISAYISI": null,
      "PORTFOYBUYUKLUK": null,
      "BilFiyat": "-"
    },
    {
      "TARIH": "1768176000000",
      "FONKODU": "HVI",
      "FONUNVAN": "DENİZ PORTFÖY HOLDİNGLER VE İŞTİRAKLERİ HİSSE SENEDİ (TL) FONU (HİSSE SENEDİ YOĞUN FON)",
      "FIYAT": 1.11784,
      "TEDPAYSAYISI": null,
      "KISISAYISI": null,
      "PORTFOYBUYUKLUK": null,
      "BilFiyat": "-"
    },
    {
      "TARIH": "1768262400000",
      "FONKODU": "HVI",
      "FONUNVAN": "DENİZ PORTFÖY HOLDİNGLER VE İŞTİRAKLERİ HİSSE SENEDİ (TL) FONU (HİSSE SENEDİ YOĞUN FON)",
      "FIYAT": 1.124546,
      "TEDPAYSAYISI": null,
      "KISISAYISI": null,
      "PORTFOYBUYUKLUK": null,
      "BilFiyat": "-"
    },
    {
      "TARIH": "1768348800000",
      "FONKODU": "HVI",
      "FONUNVAN": "DENİZ PORTFÖY HOLDİNGLER VE İŞTİRAKLERİ HİSSE SENEDİ (TL) FONU (HİSSE SENEDİ YOĞUN FON)",
      "FIYAT": 1.132071,
      "TEDPAYSAYISI": null,
      "KISISAYISI": null,
      "PORTFOYBUYUKLUK": null,
      "BilFiyat": "-"
    },
    {
      "TARIH": "1768435200000",
      "FONKODU": "HVI",
      "FONUNVAN": "DENİZ PORTFÖY HOLDİNGLER VE İŞTİRAKLERİ HİSSE SENEDİ (TL) FONU (HİSSE SENEDİ YOĞUN FON)",
      "FIYAT": 1.13617,
      "TEDPAYSAYISI": null,
      "KISISAYISI": null,
      "PORTFOYBUYUKLUK": null,
      "BilFiyat": "-"
    },
    {
      "TARIH": "1768521600000",
      "FONKODU": "HVI",
      "FONUNVAN": "DENİZ PORTFÖY HOLDİNGLER VE İŞTİRAKLERİ HİSSE SENEDİ (TL) FONU (HİSSE SENEDİ YOĞUN FON)",
      "FIYAT": 1.14887,
      "TEDPAYSAYISI": null,
      "KISISAYISI": null,
      "PORTFOYBUYUKLUK": null,
      "BilFiyat": "-"
    },
    {
      "TARIH": "1768780800000",
      "FONKODU": "HVI",
      "FONUNVAN": "DENİZ PORTFÖY HOLDİNGLER VE İŞTİRAKLERİ HİSSE SENEDİ (TL) FONU (HİSSE SENEDİ YOĞUN FON)",
      "FIYAT": 1.161543,
      "TEDPAYSAYISI": null,
      "KISISAYISI": null,
      "PORTFOYBUYUKLUK": null,
      "BilFiyat": "-"
    },
    {
      "TARIH": "1768867200000",
      "FONKODU": "HVI",
      "FONUNVAN": "DENİZ PORTFÖY HOLDİNGLER VE İŞTİRAKLERİ HİSSE SENEDİ (TL) FONU (HİSSE SENEDİ YOĞUN FON)",
      "FIYAT": 1.158372,
      "TEDPAYSAYISI": null,
      "KISISAYISI": null,
      "PORTFOYBUYUKLUK": null,
      "BilFiyat": "-"
    },
    {
      "TARIH": "1768953600000",
      "FONKODU": "HVI",
      "FONUNVAN": "DENİZ PORTFÖY HOLDİNGLER VE İŞTİRAKLERİ HİSSE SENEDİ (TL) FONU (HİSSE SENEDİ YOĞUN FON)",
      "FIYAT": 1.147635,
      "TEDPAYSAYISI": null,
      "KISISAYISI": null,
      "PORTFOYBUYUKLUK": null,
      "BilFiyat": "-"
    },
    {
      "TARIH": "1769040000000",
      "FONKODU": "HVI",
      "FONUNVAN": "DENİZ PORTFÖY HOLDİNGLER VE İŞTİRAKLERİ HİSSE SENEDİ (TL) FONU (HİSSE SENEDİ YOĞUN FON)",
      "FIYAT": 1.150257,
      "TEDPAYSAYISI": null,
      "KISISAYISI": null,
      "PORTFOYBUYUKLUK": null,
      "BilFiyat": "-"
    },
    {
      "TARIH": "1769126400000",
      "FONKODU": "HVI",
      "FONUNVAN": "DENİZ PORTFÖY HOLDİNGLER VE İŞTİRAKLERİ HİSSE SENEDİ (TL) FONU (HİSSE SENEDİ YOĞUN FON)",
      "FIYAT": 1.16695,
      "TEDPAYSAYISI": null,
      "KISISAYISI": null,
      "PORTFOYBUYUKLUK": null,
      "BilFiyat": "-"
    },
    {
      "TARIH": "1769385600000",
      "FONKODU": "HVI",
      "FONUNVAN": "DENİZ PORTFÖY HOLDİNGLER VE İŞTİRAKLERİ HİSSE SENEDİ (TL) FONU (HİSSE SENEDİ YOĞUN FON)",
      "FIYAT": 1.178437,
      "TEDPAYSAYISI": null,
      "KISISAYISI": null,
      "PORTFOYBUYUKLUK": null,
      "BilFiyat": "-"
    },
    {
      "TARIH": "1769472000000",
      "FONKODU": "HVI",
      "FONUNVAN": "DENİZ PORTFÖY HOLDİNGLER VE İŞTİRAKLERİ HİSSE SENEDİ (TL) FONU (HİSSE SENEDİ YOĞUN FON)",
      "FIYAT": 1.1884,
      "TEDPAYSAYISI": null,
      "KISISAYISI": null,
      "PORTFOYBUYUKLUK": null,
      "BilFiyat": "-"
    },
    {
      "TARIH": "1769558400000",
      "FONKODU": "HVI",
      "FONUNVAN": "DENİZ PORTFÖY HOLDİNGLER VE İŞTİRAKLERİ HİSSE SENEDİ (TL) FONU (HİSSE SENEDİ YOĞUN FON)",
      "FIYAT": 1.186739,
      "TEDPAYSAYISI": null,
      "KISISAYISI": null,
      "PORTFOYBUYUKLUK": null,
      "BilFiyat": "-"
    },
    {
      "TARIH": "1769644800000",
      "FONKODU": "HVI",
      "FONUNVAN": "DENİZ PORTFÖY HOLDİNGLER VE İŞTİRAKLERİ HİSSE SENEDİ (TL) FONU (HİSSE SENEDİ YOĞUN FON)",
      "FIYAT": 1.217032,
      "TEDPAYSAYISI": null,
      "KISISAYISI": null,
      "PORTFOYBUYUKLUK": null,
      "BilFiyat": "-"
    },
    {
      "TARIH": "1769731200000",
      "FONKODU": "HVI",
      "FONUNVAN": "DENİZ PORTFÖY HOLDİNGLER VE İŞTİRAKLERİ HİSSE SENEDİ (TL) FONU (HİSSE SENEDİ YOĞUN FON)",
      "FIYAT": 1.23769,
      "TEDPAYSAYISI": null,
      "KISISAYISI": null,
      "PORTFOYBUYUKLUK": null,
      "BilFiyat": "-"
    },
    {
      "TARIH": "1769990400000",
      "FONKODU": "HVI",
      "FONUNVAN": "DENİZ PORTFÖY HOLDİNGLER VE İŞTİRAKLERİ HİSSE SENEDİ (TL) FONU (HİSSE SENEDİ YOĞUN FON)",
      "FIYAT": 1.246336,
      "TEDPAYSAYISI": null,
      "KISISAYISI": null,
      "PORTFOYBUYUKLUK": null,
      "BilFiyat": "-"
    },
    {
      "TARIH": "1770076800000",
      "FONKODU": "HVI",
      "FONUNVAN": "DENİZ PORTFÖY HOLDİNGLER VE İŞTİRAKLERİ HİSSE SENEDİ (TL) FONU (HİSSE SENEDİ YOĞUN FON)",
      "FIYAT": 1.241689,
      "TEDPAYSAYISI": null,
      "KISISAYISI": null,
      "PORTFOYBUYUKLUK": null,
      "BilFiyat": "-"
    },
    {
      "TARIH": "1770163200000",
      "FONKODU": "HVI",
      "FONUNVAN": "DENİZ PORTFÖY HOLDİNGLER VE İŞTİRAKLERİ HİSSE SENEDİ (TL) FONU (HİSSE SENEDİ YOĞUN FON)",
      "FIYAT": 1.264488,
      "TEDPAYSAYISI": null,
      "KISISAYISI": null,
      "PORTFOYBUYUKLUK": null,
      "BilFiyat": "-"
    },
    {
      "TARIH": "1770249600000",
      "FONKODU": "HVI",
      "FONUNVAN": "DENİZ PORTFÖY HOLDİNGLER VE İŞTİRAKLERİ HİSSE SENEDİ (TL) FONU (HİSSE SENEDİ YOĞUN FON)",
      "FIYAT": 1.267414,
      "TEDPAYSAYISI": null,
      "KISISAYISI": null,
      "PORTFOYBUYUKLUK": null,
      "BilFiyat": "-"
    },
    {
      "TARIH": "1770336000000",
      "FONKODU": "HVI",
      "FONUNVAN": "DENİZ PORTFÖY HOLDİNGLER VE İŞTİRAKLERİ HİSSE SENEDİ (TL) FONU (HİSSE SENEDİ YOĞUN FON)",
      "FIYAT": 1.24277,
      "TEDPAYSAYISI": null,
      "KISISAYISI": null,
      "PORTFOYBUYUKLUK": null,
      "BilFiyat": "-"
    },
    {
      "TARIH": "1770595200000",
      "FONKODU": "HVI",
      "FONUNVAN": "DENİZ PORTFÖY HOLDİNGLER VE İŞTİRAKLERİ HİSSE SENEDİ (TL) FONU (HİSSE SENEDİ YOĞUN FON)",
      "FIYAT": 1.240873,
      "TEDPAYSAYISI": null,
      "KISISAYISI": null,
      "PORTFOYBUYUKLUK": null,
      "BilFiyat": "-"
    },
    {
      "TARIH": "1770681600000",
      "FONKODU": "HVI",
      "FONUNVAN": "DENİZ PORTFÖY HOLDİNGLER VE İŞTİRAKLERİ HİSSE SENEDİ (TL) FONU (HİSSE SENEDİ YOĞUN FON)",
      "FIYAT": 1.270004,
      "TEDPAYSAYISI": null,
      "KISISAYISI": null,
      "PORTFOYBUYUKLUK": null,
      "BilFiyat": "-"
    },
    {
      "TARIH": "1770768000000",
      "FONKODU": "HVI",
      "FONUNVAN": "DENİZ PORTFÖY HOLDİNGLER VE İŞTİRAKLERİ HİSSE SENEDİ (TL) FONU (HİSSE SENEDİ YOĞUN FON)",
      "FIYAT": 1.25515,
      "TEDPAYSAYISI": null,
      "KISISAYISI": null,
      "PORTFOYBUYUKLUK": null,
      "BilFiyat": "-"
    },
    {
      "TARIH": "1770854400000",
      "FONKODU": "HVI",
      "FONUNVAN": "DENİZ PORTFÖY HOLDİNGLER VE İŞTİRAKLERİ HİSSE SENEDİ (TL) FONU (HİSSE SENEDİ YOĞUN FON)",
      "FIYAT": 1.262635,
      "TEDPAYSAYISI": null,
      "KISISAYISI": null,
      "PORTFOYBUYUKLUK": null,
      "BilFiyat": "-"
    },
    {
      "TARIH": "1770940800000",
      "FONKODU": "HVI",
      "FONUNVAN": "DENİZ PORTFÖY HOLDİNGLER VE İŞTİRAKLERİ HİSSE SENEDİ (TL) FONU (HİSSE SENEDİ YOĞUN FON)",
      "FIYAT": 1.304836,
      "TEDPAYSAYISI": null,
      "KISISAYISI": null,
      "PORTFOYBUYUKLUK": null,
      "BilFiyat": "-"
    },
    {
      "TARIH": "1771200000000",
      "FONKODU": "HVI",
      "FONUNVAN": "DENİZ PORTFÖY HOLDİNGLER VE İŞTİRAKLERİ HİSSE SENEDİ (TL) FONU (HİSSE SENEDİ YOĞUN FON)",
      "FIYAT": 1.308606,
      "TEDPAYSAYISI": null,
      "KISISAYISI": null,
      "PORTFOYBUYUKLUK": null,
      "BilFiyat": "-"
    },
    {
      "TARIH": "1771286400000",
      "FONKODU": "HVI",
      "FONUNVAN": "DENİZ PORTFÖY HOLDİNGLER VE İŞTİRAKLERİ HİSSE SENEDİ (TL) FONU (HİSSE SENEDİ YOĞUN FON)",
      "FIYAT": 1.323244,
      "TEDPAYSAYISI": null,
      "KISISAYISI": null,
      "PORTFOYBUYUKLUK": null,
      "BilFiyat": "-"
    },
    {
      "TARIH": "1771372800000",
      "FONKODU": "HVI",
      "FONUNVAN": "DENİZ PORTFÖY HOLDİNGLER VE İŞTİRAKLERİ HİSSE SENEDİ (TL) FONU (HİSSE SENEDİ YOĞUN FON)",
      "FIYAT": 1.309344,
      "TEDPAYSAYISI": null,
      "KISISAYISI": null,
      "PORTFOYBUYUKLUK": null,
      "BilFiyat": "-"
    },
    {
      "TARIH": "1771459200000",
      "FONKODU": "HVI",
      "FONUNVAN": "DENİZ PORTFÖY HOLDİNGLER VE İŞTİRAKLERİ HİSSE SENEDİ (TL) FONU (HİSSE SENEDİ YOĞUN FON)",
      "FIYAT": 1.293365,
      "TEDPAYSAYISI": null,
      "KISISAYISI": null,
      "PORTFOYBUYUKLUK": null,
      "BilFiyat": "-"
    },
    {
      "TARIH": "1771545600000",
      "FONKODU": "HVI",
      "FONUNVAN": "DENİZ PORTFÖY HOLDİNGLER VE İŞTİRAKLERİ HİSSE SENEDİ (TL) FONU (HİSSE SENEDİ YOĞUN FON)",
      "FIYAT": 1.245538,
      "TEDPAYSAYISI": null,
      "KISISAYISI": null,
      "PORTFOYBUYUKLUK": null,
      "BilFiyat": "-"
    },
    {
      "TARIH": "1771804800000",
      "FONKODU": "HVI",
      "FONUNVAN": "DENİZ PORTFÖY HOLDİNGLER VE İŞTİRAKLERİ HİSSE SENEDİ (TL) FONU (HİSSE SENEDİ YOĞUN FON)",
      "FIYAT": 1.253288,
      "TEDPAYSAYISI": null,
      "KISISAYISI": null,
      "PORTFOYBUYUKLUK": null,
      "BilFiyat": "-"
    },
    {
      "TARIH": "1771891200000",
      "FONKODU": "HVI",
      "FONUNVAN": "DENİZ PORTFÖY HOLDİNGLER VE İŞTİRAKLERİ HİSSE SENEDİ (TL) FONU (HİSSE SENEDİ YOĞUN FON)",
      "FIYAT": 1.263673,
      "TEDPAYSAYISI": null,
      "KISISAYISI": null,
      "PORTFOYBUYUKLUK": null,
      "BilFiyat": "-"
    },
    {
      "TARIH": "1771977600000",
      "FONKODU": "HVI",
      "FONUNVAN": "DENİZ PORTFÖY HOLDİNGLER VE İŞTİRAKLERİ HİSSE SENEDİ (TL) FONU (HİSSE SENEDİ YOĞUN FON)",
      "FIYAT": 1.260838,
      "TEDPAYSAYISI": null,
      "KISISAYISI": null,
      "PORTFOYBUYUKLUK": null,
      "BilFiyat": "-"
    },
    {
      "TARIH": "1772064000000",
      "FONKODU": "HVI",
      "FONUNVAN": "DENİZ PORTFÖY HOLDİNGLER VE İŞTİRAKLERİ HİSSE SENEDİ (TL) FONU (HİSSE SENEDİ YOĞUN FON)",
      "FIYAT": 1.238717,
      "TEDPAYSAYISI": null,
      "KISISAYISI": null,
      "PORTFOYBUYUKLUK": null,
      "BilFiyat": "-"
    },
    {
      "TARIH": "1772150400000",
      "FONKODU": "HVI",
      "FONUNVAN": "DENİZ PORTFÖY HOLDİNGLER VE İŞTİRAKLERİ HİSSE SENEDİ (TL) FONU (HİSSE SENEDİ YOĞUN FON)",
      "FIYAT": 1.242027,
      "TEDPAYSAYISI": null,
      "KISISAYISI": null,
      "PORTFOYBUYUKLUK": null,
      "BilFiyat": "-"
    },
    {
      "TARIH": "1772409600000",
      "FONKODU": "HVI",
      "FONUNVAN": "DENİZ PORTFÖY HOLDİNGLER VE İŞTİRAKLERİ HİSSE SENEDİ (TL) FONU (HİSSE SENEDİ YOĞUN FON)",
      "FIYAT": 1.213224,
      "TEDPAYSAYISI": null,
      "KISISAYISI": null,
      "PORTFOYBUYUKLUK": null,
      "BilFiyat": "-"
    },
    {
      "TARIH": "1772496000000",
      "FONKODU": "HVI",
      "FONUNVAN": "DENİZ PORTFÖY HOLDİNGLER VE İŞTİRAKLERİ HİSSE SENEDİ (TL) FONU (HİSSE SENEDİ YOĞUN FON)",
      "FIYAT": 1.180069,
      "TEDPAYSAYISI": null,
      "KISISAYISI": null,
      "PORTFOYBUYUKLUK": null,
      "BilFiyat": "-"
    },
    {
      "TARIH": "1772582400000",
      "FONKODU": "HVI",
      "FONUNVAN": "DENİZ PORTFÖY HOLDİNGLER VE İŞTİRAKLERİ HİSSE SENEDİ (TL) FONU (HİSSE SENEDİ YOĞUN FON)",
      "FIYAT": 1.149796,
      "TEDPAYSAYISI": null,
      "KISISAYISI": null,
      "PORTFOYBUYUKLUK": null,
      "BilFiyat": "-"
    },
    {
      "TARIH": "1772668800000",
      "FONKODU": "HVI",
      "FONUNVAN": "DENİZ PORTFÖY HOLDİNGLER VE İŞTİRAKLERİ HİSSE SENEDİ (TL) FONU (HİSSE SENEDİ YOĞUN FON)",
      "FIYAT": 1.153999,
      "TEDPAYSAYISI": null,
      "KISISAYISI": null,
      "PORTFOYBUYUKLUK": null,
      "BilFiyat": "-"
    },
    {
      "TARIH": "1772755200000",
      "FONKODU": "HVI",
      "FONUNVAN": "DENİZ PORTFÖY HOLDİNGLER VE İŞTİRAKLERİ HİSSE SENEDİ (TL) FONU (HİSSE SENEDİ YOĞUN FON)",
      "FIYAT": 1.16392,
      "TEDPAYSAYISI": null,
      "KISISAYISI": null,
      "PORTFOYBUYUKLUK": null,
      "BilFiyat": "-"
    },
    {
      "TARIH": "1773014400000",
      "FONKODU": "HVI",
      "FONUNVAN": "DENİZ PORTFÖY HOLDİNGLER VE İŞTİRAKLERİ HİSSE SENEDİ (TL) FONU (HİSSE SENEDİ YOĞUN FON)",
      "FIYAT": 1.128386,
      "TEDPAYSAYISI": null,
      "KISISAYISI": null,
      "PORTFOYBUYUKLUK": null,
      "BilFiyat": "-"
    },
    {
      "TARIH": "1773100800000",
      "FONKODU": "HVI",
      "FONUNVAN": "DENİZ PORTFÖY HOLDİNGLER VE İŞTİRAKLERİ HİSSE SENEDİ (TL) FONU (HİSSE SENEDİ YOĞUN FON)",
      "FIYAT": 1.127821,
      "TEDPAYSAYISI": null,
      "KISISAYISI": null,
      "PORTFOYBUYUKLUK": null,
      "BilFiyat": "-"
    },
    {
      "TARIH": "1773187200000",
      "FONKODU": "HVI",
      "FONUNVAN": "DENİZ PORTFÖY HOLDİNGLER VE İŞTİRAKLERİ HİSSE SENEDİ (TL) FONU (HİSSE SENEDİ YOĞUN FON)",
      "FIYAT": 1.171444,
      "TEDPAYSAYISI": null,
      "KISISAYISI": null,
      "PORTFOYBUYUKLUK": null,
      "BilFiyat": "-"
    },
    {
      "TARIH": "1773273600000",
      "FONKODU": "HVI",
      "FONUNVAN": "DENİZ PORTFÖY HOLDİNGLER VE İŞTİRAKLERİ HİSSE SENEDİ (TL) FONU (HİSSE SENEDİ YOĞUN FON)",
      "FIYAT": 1.171978,
      "TEDPAYSAYISI": null,
      "KISISAYISI": null,
      "PORTFOYBUYUKLUK": null,
      "BilFiyat": "-"
    },
    {
      "TARIH": "1773360000000",
      "FONKODU": "HVI",
      "FONUNVAN": "DENİZ PORTFÖY HOLDİNGLER VE İŞTİRAKLERİ HİSSE SENEDİ (TL) FONU (HİSSE SENEDİ YOĞUN FON)",
      "FIYAT": 1.171896,
      "TEDPAYSAYISI": null,
      "KISISAYISI": null,
      "PORTFOYBUYUKLUK": null,
      "BilFiyat": "-"
    },
    {
      "TARIH": "1773619200000",
      "FONKODU": "HVI",
      "FONUNVAN": "DENİZ PORTFÖY HOLDİNGLER VE İŞTİRAKLERİ HİSSE SENEDİ (TL) FONU (HİSSE SENEDİ YOĞUN FON)",
      "FIYAT": 1.162155,
      "TEDPAYSAYISI": null,
      "KISISAYISI": null,
      "PORTFOYBUYUKLUK": null,
      "BilFiyat": "-"
    },
    {
      "TARIH": "1773705600000",
      "FONKODU": "HVI",
      "FONUNVAN": "DENİZ PORTFÖY HOLDİNGLER VE İŞTİRAKLERİ HİSSE SENEDİ (TL) FONU (HİSSE SENEDİ YOĞUN FON)",
      "FIYAT": 1.15337,
      "TEDPAYSAYISI": null,
      "KISISAYISI": null,
      "PORTFOYBUYUKLUK": null,
      "BilFiyat": "-"
    },
    {
      "TARIH": "1773792000000",
      "FONKODU": "HVI",
      "FONUNVAN": "DENİZ PORTFÖY HOLDİNGLER VE İŞTİRAKLERİ HİSSE SENEDİ (TL) FONU (HİSSE SENEDİ YOĞUN FON)",
      "FIYAT": 1.17241,
      "TEDPAYSAYISI": null,
      "KISISAYISI": null,
      "PORTFOYBUYUKLUK": null,
      "BilFiyat": "-"
    },
    {
      "TARIH": "1773878400000",
      "FONKODU": "HVI",
      "FONUNVAN": "DENİZ PORTFÖY HOLDİNGLER VE İŞTİRAKLERİ HİSSE SENEDİ (TL) FONU (HİSSE SENEDİ YOĞUN FON)",
      "FIYAT": 1.15647,
      "TEDPAYSAYISI": null,
      "KISISAYISI": null,
      "PORTFOYBUYUKLUK": null,
      "BilFiyat": "-"
    },
    {
      "TARIH": "1774224000000",
      "FONKODU": "HVI",
      "FONUNVAN": "DENİZ PORTFÖY HOLDİNGLER VE İŞTİRAKLERİ HİSSE SENEDİ (TL) FONU (HİSSE SENEDİ YOĞUN FON)",
      "FIYAT": 1.155687,
      "TEDPAYSAYISI": null,
      "KISISAYISI": null,
      "PORTFOYBUYUKLUK": null,
      "BilFiyat": "-"
    },
    {
      "TARIH": "1774310400000",
      "FONKODU": "HVI",
      "FONUNVAN": "DENİZ PORTFÖY HOLDİNGLER VE İŞTİRAKLERİ HİSSE SENEDİ (TL) FONU (HİSSE SENEDİ YOĞUN FON)",
      "FIYAT": 1.162299,
      "TEDPAYSAYISI": null,
      "KISISAYISI": null,
      "PORTFOYBUYUKLUK": null,
      "BilFiyat": "-"
    },
    {
      "TARIH": "1774396800000",
      "FONKODU": "HVI",
      "FONUNVAN": "DENİZ PORTFÖY HOLDİNGLER VE İŞTİRAKLERİ HİSSE SENEDİ (TL) FONU (HİSSE SENEDİ YOĞUN FON)",
      "FIYAT": 1.144853,
      "TEDPAYSAYISI": null,
      "KISISAYISI": null,
      "PORTFOYBUYUKLUK": null,
      "BilFiyat": "-"
    },
    {
      "TARIH": "1774483200000",
      "FONKODU": "HVI",
      "FONUNVAN": "DENİZ PORTFÖY HOLDİNGLER VE İŞTİRAKLERİ HİSSE SENEDİ (TL) FONU (HİSSE SENEDİ YOĞUN FON)",
      "FIYAT": 1.157033,
      "TEDPAYSAYISI": null,
      "KISISAYISI": null,
      "PORTFOYBUYUKLUK": null,
      "BilFiyat": "-"
    },
    {
      "TARIH": "1774569600000",
      "FONKODU": "HVI",
      "FONUNVAN": "DENİZ PORTFÖY HOLDİNGLER VE İŞTİRAKLERİ HİSSE SENEDİ (TL) FONU (HİSSE SENEDİ YOĞUN FON)",
      "FIYAT": 1.14553,
      "TEDPAYSAYISI": null,
      "KISISAYISI": null,
      "PORTFOYBUYUKLUK": null,
      "BilFiyat": "-"
    },
    {
      "TARIH": "1774828800000",
      "FONKODU": "HVI",
      "FONUNVAN": "DENİZ PORTFÖY HOLDİNGLER VE İŞTİRAKLERİ HİSSE SENEDİ (TL) FONU (HİSSE SENEDİ YOĞUN FON)",
      "FIYAT": 1.143102,
      "TEDPAYSAYISI": null,
      "KISISAYISI": null,
      "PORTFOYBUYUKLUK": null,
      "BilFiyat": "-"
    },
    {
      "TARIH": "1774915200000",
      "FONKODU": "HVI",
      "FONUNVAN": "DENİZ PORTFÖY HOLDİNGLER VE İŞTİRAKLERİ HİSSE SENEDİ (TL) FONU (HİSSE SENEDİ YOĞUN FON)",
      "FIYAT": 1.137357,
      "TEDPAYSAYISI": null,
      "KISISAYISI": null,
      "PORTFOYBUYUKLUK": null,
      "BilFiyat": "-"
    },
    {
      "TARIH": "1775001600000",
      "FONKODU": "HVI",
      "FONUNVAN": "DENİZ PORTFÖY HOLDİNGLER VE İŞTİRAKLERİ HİSSE SENEDİ (TL) FONU (HİSSE SENEDİ YOĞUN FON)",
      "FIYAT": 1.153161,
      "TEDPAYSAYISI": null,
      "KISISAYISI": null,
      "PORTFOYBUYUKLUK": null,
      "BilFiyat": "-"
    },
    {
      "TARIH": "1775088000000",
      "FONKODU": "HVI",
      "FONUNVAN": "DENİZ PORTFÖY HOLDİNGLER VE İŞTİRAKLERİ HİSSE SENEDİ (TL) FONU (HİSSE SENEDİ YOĞUN FON)",
      "FIYAT": 1.172407,
      "TEDPAYSAYISI": null,
      "KISISAYISI": null,
      "PORTFOYBUYUKLUK": null,
      "BilFiyat": "-"
    },
    {
      "TARIH": "1775174400000",
      "FONKODU": "HVI",
      "FONUNVAN": "DENİZ PORTFÖY HOLDİNGLER VE İŞTİRAKLERİ HİSSE SENEDİ (TL) FONU (HİSSE SENEDİ YOĞUN FON)",
      "FIYAT": 1.177886,
      "TEDPAYSAYISI": null,
      "KISISAYISI": null,
      "PORTFOYBUYUKLUK": null,
      "BilFiyat": "-"
    },
    {
      "TARIH": "1775433600000",
      "FONKODU": "HVI",
      "FONUNVAN": "DENİZ PORTFÖY HOLDİNGLER VE İŞTİRAKLERİ HİSSE SENEDİ (TL) FONU (HİSSE SENEDİ YOĞUN FON)",
      "FIYAT": 1.170564,
      "TEDPAYSAYISI": null,
      "KISISAYISI": null,
      "PORTFOYBUYUKLUK": null,
      "BilFiyat": "-"
    },
    {
      "TARIH": "1775520000000",
      "FONKODU": "HVI",
      "FONUNVAN": "DENİZ PORTFÖY HOLDİNGLER VE İŞTİRAKLERİ HİSSE SENEDİ (TL) FONU (HİSSE SENEDİ YOĞUN FON)",
      "FIYAT": 1.184442,
      "TEDPAYSAYISI": null,
      "KISISAYISI": null,
      "PORTFOYBUYUKLUK": null,
      "BilFiyat": "-"
    },
    {
      "TARIH": "1775606400000",
      "FONKODU": "HVI",
      "FONUNVAN": "DENİZ PORTFÖY HOLDİNGLER VE İŞTİRAKLERİ HİSSE SENEDİ (TL) FONU (HİSSE SENEDİ YOĞUN FON)",
      "FIYAT": 1.157975,
      "TEDPAYSAYISI": null,
      "KISISAYISI": null,
      "PORTFOYBUYUKLUK": null,
      "BilFiyat": "-"
    },
    {
      "TARIH": "1775692800000",
      "FONKODU": "HVI",
      "FONUNVAN": "DENİZ PORTFÖY HOLDİNGLER VE İŞTİRAKLERİ HİSSE SENEDİ (TL) FONU (HİSSE SENEDİ YOĞUN FON)",
      "FIYAT": 1.215973,
      "TEDPAYSAYISI": null,
      "KISISAYISI": null,
      "PORTFOYBUYUKLUK": null,
      "BilFiyat": "-"
    },
    {
      "TARIH": "1775779200000",
      "FONKODU": "HVI",
      "FONUNVAN": "DENİZ PORTFÖY HOLDİNGLER VE İŞTİRAKLERİ HİSSE SENEDİ (TL) FONU (HİSSE SENEDİ YOĞUN FON)",
      "FIYAT": 1.228077,
      "TEDPAYSAYISI": null,
      "KISISAYISI": null,
      "PORTFOYBUYUKLUK": null,
      "BilFiyat": "-"
    },
    {
      "TARIH": "1776038400000",
      "FONKODU": "HVI",
      "FONUNVAN": "DENİZ PORTFÖY HOLDİNGLER VE İŞTİRAKLERİ HİSSE SENEDİ (TL) FONU (HİSSE SENEDİ YOĞUN FON)",
      "FIYAT": 1.25656,
      "TEDPAYSAYISI": null,
      "KISISAYISI": null,
      "PORTFOYBUYUKLUK": null,
      "BilFiyat": "-"
    },
    {
      "TARIH": "1776124800000",
      "FONKODU": "HVI",
      "FONUNVAN": "DENİZ PORTFÖY HOLDİNGLER VE İŞTİRAKLERİ HİSSE SENEDİ (TL) FONU (HİSSE SENEDİ YOĞUN FON)",
      "FIYAT": 1.247925,
      "TEDPAYSAYISI": null,
      "KISISAYISI": null,
      "PORTFOYBUYUKLUK": null,
      "BilFiyat": "-"
    },
    {
      "TARIH": "1776211200000",
      "FONKODU": "HVI",
      "FONUNVAN": "DENİZ PORTFÖY HOLDİNGLER VE İŞTİRAKLERİ HİSSE SENEDİ (TL) FONU (HİSSE SENEDİ YOĞUN FON)",
      "FIYAT": 1.263896,
      "TEDPAYSAYISI": null,
      "KISISAYISI": null,
      "PORTFOYBUYUKLUK": null,
      "BilFiyat": "-"
    },
    {
      "TARIH": "1776297600000",
      "FONKODU": "HVI",
      "FONUNVAN": "DENİZ PORTFÖY HOLDİNGLER VE İŞTİRAKLERİ HİSSE SENEDİ (TL) FONU (HİSSE SENEDİ YOĞUN FON)",
      "FIYAT": 1.266291,
      "TEDPAYSAYISI": null,
      "KISISAYISI": null,
      "PORTFOYBUYUKLUK": null,
      "BilFiyat": "-"
    },
    {
      "TARIH": "1776384000000",
      "FONKODU": "HVI",
      "FONUNVAN": "DENİZ PORTFÖY HOLDİNGLER VE İŞTİRAKLERİ HİSSE SENEDİ (TL) FONU (HİSSE SENEDİ YOĞUN FON)",
      "FIYAT": 1.258601,
      "TEDPAYSAYISI": null,
      "KISISAYISI": null,
      "PORTFOYBUYUKLUK": null,
      "BilFiyat": "-"
    },
    {
      "TARIH": "1776643200000",
      "FONKODU": "HVI",
      "FONUNVAN": "DENİZ PORTFÖY HOLDİNGLER VE İŞTİRAKLERİ HİSSE SENEDİ (TL) FONU (HİSSE SENEDİ YOĞUN FON)",
      "FIYAT": 1.29153,
      "TEDPAYSAYISI": null,
      "KISISAYISI": null,
      "PORTFOYBUYUKLUK": null,
      "BilFiyat": "-"
    },
    {
      "TARIH": "1776729600000",
      "FONKODU": "HVI",
      "FONUNVAN": "DENİZ PORTFÖY HOLDİNGLER VE İŞTİRAKLERİ HİSSE SENEDİ (TL) FONU (HİSSE SENEDİ YOĞUN FON)",
      "FIYAT": 1.27828,
      "TEDPAYSAYISI": null,
      "KISISAYISI": null,
      "PORTFOYBUYUKLUK": null,
      "BilFiyat": "-"
    },
    {
      "TARIH": "1776816000000",
      "FONKODU": "HVI",
      "FONUNVAN": "DENİZ PORTFÖY HOLDİNGLER VE İŞTİRAKLERİ HİSSE SENEDİ (TL) FONU (HİSSE SENEDİ YOĞUN FON)",
      "FIYAT": 1.273238,
      "TEDPAYSAYISI": null,
      "KISISAYISI": null,
      "PORTFOYBUYUKLUK": null,
      "BilFiyat": "-"
    },
    {
      "TARIH": "1776988800000",
      "FONKODU": "HVI",
      "FONUNVAN": "DENİZ PORTFÖY HOLDİNGLER VE İŞTİRAKLERİ HİSSE SENEDİ (TL) FONU (HİSSE SENEDİ YOĞUN FON)",
      "FIYAT": 1.264051,
      "TEDPAYSAYISI": null,
      "KISISAYISI": null,
      "PORTFOYBUYUKLUK": null,
      "BilFiyat": "-"
    },
    {
      "TARIH": "1777248000000",
      "FONKODU": "HVI",
      "FONUNVAN": "DENİZ PORTFÖY HOLDİNGLER VE İŞTİRAKLERİ HİSSE SENEDİ (TL) FONU (HİSSE SENEDİ YOĞUN FON)",
      "FIYAT": 1.263347,
      "TEDPAYSAYISI": null,
      "KISISAYISI": null,
      "PORTFOYBUYUKLUK": null,
      "BilFiyat": "-"
    },
    {
      "TARIH": "1777334400000",
      "FONKODU": "HVI",
      "FONUNVAN": "DENİZ PORTFÖY HOLDİNGLER VE İŞTİRAKLERİ HİSSE SENEDİ (TL) FONU (HİSSE SENEDİ YOĞUN FON)",
      "FIYAT": 1.26616,
      "TEDPAYSAYISI": null,
      "KISISAYISI": null,
      "PORTFOYBUYUKLUK": null,
      "BilFiyat": "-"
    },
    {
      "TARIH": "1777420800000",
      "FONKODU": "HVI",
      "FONUNVAN": "DENİZ PORTFÖY HOLDİNGLER VE İŞTİRAKLERİ HİSSE SENEDİ (TL) FONU (HİSSE SENEDİ YOĞUN FON)",
      "FIYAT": 1.251325,
      "TEDPAYSAYISI": null,
      "KISISAYISI": null,
      "PORTFOYBUYUKLUK": null,
      "BilFiyat": "-"
    }
  ]
}